contact_form/__init__.py
contact_form/settings.py
contact_form/urls.py
contact_form/wsgi.py
emencia_contact_form/__init__.py
emencia_contact_form/admin.py
emencia_contact_form/apps.py
emencia_contact_form/checks.py
emencia_contact_form/choices.py
emencia_contact_form/cms_app.py
emencia_contact_form/fields.py
emencia_contact_form/forms.py
emencia_contact_form/forms_utils.py
emencia_contact_form/mails.py
emencia_contact_form/models.py
emencia_contact_form/sitemaps.py
emencia_contact_form/translation.py
emencia_contact_form/urls.py
emencia_contact_form/views.py
emencia_contact_form/locale/fr/LC_MESSAGES/django.po
emencia_contact_form/migrations/0001_initial.py
emencia_contact_form/migrations/0002_data_migration.py
emencia_contact_form/migrations/__init__.py
emencia_contact_form/templates/contact_form/base.html
emencia_contact_form/templates/contact_form/contact_form.html
emencia_contact_form/templates/contact_form/contact_form_message.txt
emencia_contact_form/templates/contact_form/contact_form_success.html
emencia_contact_form/tests/__init__.py
emencia_contact_form/tests/tests_checks.py
emencia_contact_form/tests/tests_cms_app.py
emencia_contact_form/tests/tests_forms_utils.py
emencia_contact_form/tests/tests_mails.py
emencia_contact_form/tests/tests_models.py
emencia_contact_form/tests/tests_sitemaps.py
emencia_contact_form/tests/tests_views.py
emencia_contact_form-0.3.dist-info/DESCRIPTION.rst
emencia_contact_form-0.3.dist-info/METADATA
emencia_contact_form-0.3.dist-info/RECORD
emencia_contact_form-0.3.dist-info/WHEEL
emencia_contact_form-0.3.dist-info/metadata.json
emencia_contact_form-0.3.dist-info/top_level.txt
