Metadata-Version: 2.0
Name: emencia-contact-form
Version: 0.3
Summary: A reusable app to add a basic and configurable contact form.
Home-page: https://github.com/emencia/contact_form
Author: Adrien Brunet - Emencia
Author-email: adrien@emencia.com
License: AGPL
Platform: UNKNOWN
Classifier: Environment :: Web Environment
Classifier: Framework :: Django
Classifier: Framework :: Django :: 1.10
Classifier: Intended Audience :: Developers
Classifier: License :: OSI Approved :: GNU Affero General Public License v3 or later (AGPLv3+)
Classifier: Operating System :: OS Independent
Classifier: Programming Language :: Python
Classifier: Programming Language :: Python :: 3
Classifier: Programming Language :: Python :: 3.5
Classifier: Topic :: Internet :: WWW/HTTP
Classifier: Topic :: Internet :: WWW/HTTP :: Dynamic Content
Requires-Dist: django (>=1.8,<1.11)
Requires-Dist: tox
Requires-Dist: django-countries
Requires-Dist: pytz
Requires-Dist: crispy-forms-foundation
Requires-Dist: django-modeltranslation
Requires-Dist: django-import-export
Requires-Dist: django-crispy-forms
Requires-Dist: psycopg2
Requires-Dist: django-cms (>=3)
Requires-Dist: django-recaptcha
